US_coord/US.py
US_coord/__init__.py
example_pkg_legendbone-0.0.1.dist-info/METADATA
example_pkg_legendbone-0.0.1.dist-info/WHEEL
example_pkg_legendbone-0.0.1.dist-info/top_level.txt
example_pkg_legendbone-0.0.1.dist-info/RECORD
