Metadata-Version: 2.1
Name: example-pkg-legendbone
Version: 0.0.1
Summary: Get coordinate of US state
Home-page: https://github.com/pypa/sampleproject
Author: Nic Nguyen
Author-email: nguyenhoangnguyen96nt@gmail.com
License: UNKNOWN
Platform: UNKNOWN
Classifier: Programming Language :: Python :: 3
Classifier: License :: OSI Approved :: MIT License
Classifier: Operating System :: OS Independent
Requires-Python: >=3.6
